{"_id":"pm2-axon-rpc","_rev":"28-ff28e583814bcdd678e019b51234a2f1","name":"pm2-axon-rpc","description":"Remote procedure calls built on top of axon.","dist-tags":{"latest":"0.5.0"},"versions":{"0.0.2":{"name":"pm2-axon-rpc","version":"0.0.2","description":"RPC for axon","keywords":["axon","rpc","cloud"],"author":{"name":"TJ Holowaychuk","email":"tj@learnboost.com"},"dependencies":{"debug":"*","commander":"1.0.5","json-stringify-safe":"*"},"devDependencies":{"axon":"1.0.0","better-assert":"*","mocha":"*"},"bin":{"arpc":"bin/arpc"},"main":"index","_id":"pm2-axon-rpc@0.0.2","dist":{"shasum":"7caf29a39b935f0ccbbc6296dc7871922fdb418b","tarball":"https://registry.npmjs.org/pm2-axon-rpc/-/pm2-axon-rpc-0.0.2.tgz"},"_from":".","_npmVersion":"1.3.22","_npmUser":{"name":"tknew","email":"strzelewicz.alexandre@gmail.com"},"maintainers":[{"name":"tknew","email":"strzelewicz.alexandre@gmail.com"}],"directories":{}},"0.2.0":{"name":"pm2-axon-rpc","version":"0.2.0","description":"Remote procedure calls built on top of axon.","keywords":["axon","rpc","cloud"],"author":{"name":"TJ Holowaychuk","email":"tj@learnboost.com"},"contributors":[{"name":"Bret Copeland","email":"bret@atlantisflight.org","url":"https://github.com/bretcope"}],"dependencies":{"debug":"*","commander":"1.0.5","json-stringify-safe":"*"},"devDependencies":{"axon":"2.0.0","better-assert":"*","mocha":"*"},"bin":{"arpc":"bin/arpc"},"main":"index","scripts":{"test":"mocha --reporter spec"},"repository":{"type":"git","url":"https://github.com/visionmedia/axon-rpc.git"},"license":"MIT","bugs":{"url":"https://github.com/visionmedia/axon-rpc/issues"},"homepage":"https://github.com/visionmedia/axon-rpc","_id":"pm2-axon-rpc@0.2.0","_shasum":"4f9fc5c8bccb9fc58eb18b0f5473a8238821ea1f","_from":".","_npmVersion":"1.4.9","_npmUser":{"name":"tknew","email":"strzelewicz.alexandre@gmail.com"},"maintainers":[{"name":"tknew","email":"strzelewicz.alexandre@gmail.com"}],"dist":{"shasum":"4f9fc5c8bccb9fc58eb18b0f5473a8238821ea1f","tarball":"https://registry.npmjs.org/pm2-axon-rpc/-/pm2-axon-rpc-0.2.0.tgz"},"directories":{}},"0.2.1":{"name":"pm2-axon-rpc","version":"0.2.1","description":"Remote procedure calls built on top of axon.","keywords":["axon","rpc","cloud"],"author":{"name":"TJ Holowaychuk","email":"tj@learnboost.com"},"contributors":[{"name":"Bret Copeland","email":"bret@atlantisflight.org","url":"https://github.com/bretcope"}],"dependencies":{"debug":"*","commander":"1.0.5","json-stringify-safe":"*"},"devDependencies":{"axon":"2.0.0","better-assert":"*","mocha":"*"},"bin":{"arpc":"bin/arpc"},"main":"index","scripts":{"test":"mocha --reporter spec"},"repository":{"type":"git","url":"https://github.com/visionmedia/axon-rpc.git"},"license":"MIT","bugs":{"url":"https://github.com/visionmedia/axon-rpc/issues"},"homepage":"https://github.com/visionmedia/axon-rpc","_id":"pm2-axon-rpc@0.2.1","_shasum":"4f9fc5c8bccb9fc58eb18b0f5473a8238821ea1f","_from":".","_npmVersion":"1.4.9","_npmUser":{"name":"tknew","email":"strzelewicz.alexandre@gmail.com"},"maintainers":[{"name":"tknew","email":"strzelewicz.alexandre@gmail.com"}],"dist":{"shasum":"cb25eec3881de76583b2d98cd05026d4773cb184","tarball":"https://registry.npmjs.org/pm2-axon-rpc/-/pm2-axon-rpc-0.2.1.tgz"},"directories":{}},"0.3.1":{"name":"pm2-axon-rpc","version":"0.3.1","description":"Remote procedure calls built on top of axon.","keywords":["axon","rpc","cloud"],"author":{"name":"TJ Holowaychuk","email":"tj@learnboost.com"},"contributors":[{"name":"Bret Copeland","email":"bret@atlantisflight.org","url":"https://github.com/bretcope"}],"dependencies":{"debug":"*","commander":"1.0.5","json-stringify-safe":"*"},"devDependencies":{"pm2-axon":"2.0.0","better-assert":"*","mocha":"*"},"bin":{"arpc":"bin/arpc"},"main":"index","scripts":{"test":"mocha --reporter spec"},"repository":{"type":"git","url":"https://github.com/visionmedia/axon-rpc.git"},"license":"MIT","bugs":{"url":"https://github.com/visionmedia/axon-rpc/issues"},"homepage":"https://github.com/visionmedia/axon-rpc","_id":"pm2-axon-rpc@0.3.1","_shasum":"4f9fc5c8bccb9fc58eb18b0f5473a8238821ea1f","_from":".","_resolved":"https://registry.npmjs.org/pm2-axon-rpc/-/pm2-axon-rpc-0.2.1.tgz","_npmVersion":"1.4.9","_npmUser":{"name":"tknew","email":"strzelewicz.alexandre@gmail.com"},"maintainers":[{"name":"tknew","email":"strzelewicz.alexandre@gmail.com"}],"dist":{"shasum":"b564e888457ac2027e04ac7ff328c41fc1413492","tarball":"https://registry.npmjs.org/pm2-axon-rpc/-/pm2-axon-rpc-0.3.1.tgz"},"directories":{}},"0.3.2":{"name":"pm2-axon-rpc","version":"0.3.2","description":"Remote procedure calls built on top of axon.","keywords":["axon","rpc","cloud"],"author":{"name":"TJ Holowaychuk","email":"tj@learnboost.com"},"contributors":[{"name":"Bret Copeland","email":"bret@atlantisflight.org","url":"https://github.com/bretcope"}],"dependencies":{"debug":"*","commander":"1.0.5","json-stringify-safe":"*"},"devDependencies":{"pm2-axon":"~2.0.2","better-assert":"*","mocha":"*"},"bin":{"arpc":"bin/arpc"},"main":"index","scripts":{"test":"mocha --reporter spec"},"repository":{"type":"git","url":"https://github.com/unitech/pm2-axon-rpc.git"},"license":"MIT","bugs":{"url":"https://github.com/unitech/pm2-axon-rpc/issues"},"homepage":"https://github.com/unitech/pm2-axon-rpc","_id":"pm2-axon-rpc@0.3.2","_shasum":"327eaa369abf24d1384175e6c555006734b9cd00","_from":".","_npmVersion":"1.4.9","_npmUser":{"name":"tknew","email":"strzelewicz.alexandre@gmail.com"},"maintainers":[{"name":"tknew","email":"strzelewicz.alexandre@gmail.com"}],"dist":{"shasum":"327eaa369abf24d1384175e6c555006734b9cd00","tarball":"https://registry.npmjs.org/pm2-axon-rpc/-/pm2-axon-rpc-0.3.2.tgz"},"directories":{}},"0.3.3":{"name":"pm2-axon-rpc","version":"0.3.3","description":"Remote procedure calls built on top of axon.","keywords":["axon","rpc","cloud"],"author":{"name":"TJ Holowaychuk","email":"tj@learnboost.com"},"contributors":[{"name":"Bret Copeland","email":"bret@atlantisflight.org","url":"https://github.com/bretcope"}],"dependencies":{"debug":"*","commander":"1.0.5","json-stringify-safe":"*"},"devDependencies":{"pm2-axon":"~2.0.2","better-assert":"*","mocha":"*"},"bin":{"arpc":"bin/arpc"},"main":"index","scripts":{"test":"mocha --reporter spec"},"repository":{"type":"git","url":"https://github.com/unitech/pm2-axon-rpc.git"},"license":"MIT","bugs":{"url":"https://github.com/unitech/pm2-axon-rpc/issues"},"homepage":"https://github.com/unitech/pm2-axon-rpc","_id":"pm2-axon-rpc@0.3.3","_shasum":"362d44d5e4912dd32fa36d98df65486b5d9d49f6","_from":".","_npmVersion":"1.4.9","_npmUser":{"name":"tknew","email":"strzelewicz.alexandre@gmail.com"},"maintainers":[{"name":"tknew","email":"strzelewicz.alexandre@gmail.com"}],"dist":{"shasum":"362d44d5e4912dd32fa36d98df65486b5d9d49f6","tarball":"https://registry.npmjs.org/pm2-axon-rpc/-/pm2-axon-rpc-0.3.3.tgz"},"directories":{}},"0.3.4":{"name":"pm2-axon-rpc","version":"0.3.4","description":"Remote procedure calls built on top of axon.","keywords":["axon","rpc","cloud"],"author":{"name":"TJ Holowaychuk","email":"tj@learnboost.com"},"contributors":[{"name":"Bret Copeland","email":"bret@atlantisflight.org","url":"https://github.com/bretcope"}],"dependencies":{"debug":"*","commander":"1.0.5","json-stringify-safe":"*"},"devDependencies":{"pm2-axon":"2.0.4","better-assert":"*","mocha":"*"},"bin":{"arpc":"bin/arpc"},"main":"index","scripts":{"test":"mocha --reporter spec"},"repository":{"type":"git","url":"https://github.com/unitech/pm2-axon-rpc.git"},"license":"MIT","gitHead":"64e87fbf8c7eb857d28fee903b6aff486d1e9968","bugs":{"url":"https://github.com/unitech/pm2-axon-rpc/issues"},"homepage":"https://github.com/unitech/pm2-axon-rpc","_id":"pm2-axon-rpc@0.3.4","_shasum":"45f7438f17ad32c92cd1cc8f10aca62d7271eabe","_from":".","_npmVersion":"2.0.0","_npmUser":{"name":"tknew","email":"strzelewicz.alexandre@gmail.com"},"maintainers":[{"name":"tknew","email":"strzelewicz.alexandre@gmail.com"}],"dist":{"shasum":"45f7438f17ad32c92cd1cc8f10aca62d7271eabe","tarball":"https://registry.npmjs.org/pm2-axon-rpc/-/pm2-axon-rpc-0.3.4.tgz"},"directories":{}},"0.3.5":{"name":"pm2-axon-rpc","version":"0.3.5","description":"Remote procedure calls built on top of axon.","keywords":["axon","rpc","cloud"],"author":{"name":"TJ Holowaychuk","email":"tj@learnboost.com"},"contributors":[{"name":"Bret Copeland","email":"bret@atlantisflight.org","url":"https://github.com/bretcope"}],"dependencies":{"debug":"*","commander":"1.0.5","json-stringify-safe":"*"},"devDependencies":{"pm2-axon":"~2.0.5","better-assert":"*","mocha":"*"},"bin":{"arpc":"bin/arpc"},"main":"index","scripts":{"test":"mocha --reporter spec"},"repository":{"type":"git","url":"https://github.com/unitech/pm2-axon-rpc.git"},"license":"MIT","gitHead":"aaa6d3c839f900bb99b1af6123d0158c5cf0aa5f","bugs":{"url":"https://github.com/unitech/pm2-axon-rpc/issues"},"homepage":"https://github.com/unitech/pm2-axon-rpc","_id":"pm2-axon-rpc@0.3.5","_shasum":"9059333574501f4765cda61e82a7a4bd70fd6c5d","_from":".","_npmVersion":"2.0.0","_npmUser":{"name":"tknew","email":"strzelewicz.alexandre@gmail.com"},"maintainers":[{"name":"tknew","email":"strzelewicz.alexandre@gmail.com"}],"dist":{"shasum":"9059333574501f4765cda61e82a7a4bd70fd6c5d","tarball":"https://registry.npmjs.org/pm2-axon-rpc/-/pm2-axon-rpc-0.3.5.tgz"},"directories":{}},"0.3.6":{"name":"pm2-axon-rpc","version":"0.3.6","description":"Remote procedure calls built on top of axon.","keywords":["axon","rpc","cloud"],"author":{"name":"TJ Holowaychuk","email":"tj@learnboost.com"},"contributors":[{"name":"Bret Copeland","email":"bret@atlantisflight.org","url":"https://github.com/bretcope"}],"dependencies":{"debug":"*","commander":"1.0.5","json-stringify-safe":"*"},"devDependencies":{"pm2-axon":"~2.0.7","better-assert":"*","mocha":"*"},"bin":{"arpc":"bin/arpc"},"main":"index","scripts":{"test":"mocha --reporter spec"},"repository":{"type":"git","url":"https://github.com/unitech/pm2-axon-rpc.git"},"license":"MIT","gitHead":"aaa6d3c839f900bb99b1af6123d0158c5cf0aa5f","bugs":{"url":"https://github.com/unitech/pm2-axon-rpc/issues"},"homepage":"https://github.com/unitech/pm2-axon-rpc","_id":"pm2-axon-rpc@0.3.6","_shasum":"0a8931f4f6de47bf3791633cc675b0e4700f36a0","_from":".","_npmVersion":"2.0.0","_npmUser":{"name":"tknew","email":"strzelewicz.alexandre@gmail.com"},"maintainers":[{"name":"tknew","email":"strzelewicz.alexandre@gmail.com"}],"dist":{"shasum":"0a8931f4f6de47bf3791633cc675b0e4700f36a0","tarball":"https://registry.npmjs.org/pm2-axon-rpc/-/pm2-axon-rpc-0.3.6.tgz"},"directories":{}},"0.4.0":{"name":"pm2-axon-rpc","version":"0.4.0","description":"Remote procedure calls built on top of axon.","keywords":["axon","rpc","cloud"],"author":{"name":"TJ Holowaychuk","email":"tj@learnboost.com"},"contributors":[{"name":"Bret Copeland","email":"bret@atlantisflight.org","url":"https://github.com/bretcope"}],"dependencies":{"debug":"*"},"devDependencies":{"pm2-axon":"~2.0.5","better-assert":"*","mocha":"*"},"main":"index","scripts":{"test":"mocha --reporter spec"},"repository":{"type":"git","url":"git+https://github.com/unitech/pm2-axon-rpc.git"},"license":"MIT","gitHead":"879e924aea210b856122fd967d588ba3adf03103","bugs":{"url":"https://github.com/unitech/pm2-axon-rpc/issues"},"homepage":"https://github.com/unitech/pm2-axon-rpc#readme","_id":"pm2-axon-rpc@0.4.0","_shasum":"d9403f81a591e96e91b4cbc60feebf1e963b483f","_from":".","_npmVersion":"3.8.3","_nodeVersion":"5.10.0","_npmUser":{"name":"tknew","email":"strzelewicz.alexandre@gmail.com"},"dist":{"shasum":"d9403f81a591e96e91b4cbc60feebf1e963b483f","tarball":"https://registry.npmjs.org/pm2-axon-rpc/-/pm2-axon-rpc-0.4.0.tgz"},"maintainers":[{"name":"tknew","email":"strzelewicz.alexandre@gmail.com"}],"_npmOperationalInternal":{"host":"packages-16-east.internal.npmjs.com","tmp":"tmp/pm2-axon-rpc-0.4.0.tgz_1465853123851_0.723944318946451"},"directories":{}},"0.4.2":{"name":"pm2-axon-rpc","version":"0.4.2","description":"Remote procedure calls built on top of axon.","keywords":["axon","rpc","cloud"],"author":{"name":"TJ Holowaychuk","email":"tj@learnboost.com"},"contributors":[{"name":"Bret Copeland","email":"bret@atlantisflight.org","url":"https://github.com/bretcope"}],"dependencies":{"debug":"*"},"devDependencies":{"pm2-axon":"~2.0.11","fclone":"1.0.3","better-assert":"*","mocha":"*"},"main":"index","scripts":{"test":"mocha --reporter spec"},"repository":{"type":"git","url":"git+https://github.com/unitech/pm2-axon-rpc.git"},"license":"MIT","gitHead":"a9f6e83ca73011606b4b1059f3192e0f27791470","bugs":{"url":"https://github.com/unitech/pm2-axon-rpc/issues"},"homepage":"https://github.com/unitech/pm2-axon-rpc#readme","_id":"pm2-axon-rpc@0.4.2","_shasum":"5d8b23abeed74d81334d6127eab2de1d88023314","_from":".","_npmVersion":"3.10.4","_nodeVersion":"4.4.4","_npmUser":{"name":"tknew","email":"strzelewicz.alexandre@gmail.com"},"dist":{"shasum":"5d8b23abeed74d81334d6127eab2de1d88023314","tarball":"https://registry.npmjs.org/pm2-axon-rpc/-/pm2-axon-rpc-0.4.2.tgz"},"maintainers":[{"name":"tknew","email":"strzelewicz.alexandre@gmail.com"}],"_npmOperationalInternal":{"host":"packages-16-east.internal.npmjs.com","tmp":"tmp/pm2-axon-rpc-0.4.2.tgz_1467382252507_0.9493745183572173"},"directories":{}},"0.4.3":{"name":"pm2-axon-rpc","version":"0.4.3","description":"Remote procedure calls built on top of axon.","keywords":["axon","rpc","cloud"],"author":{"name":"TJ Holowaychuk","email":"tj@learnboost.com"},"contributors":[{"name":"Bret Copeland","email":"bret@atlantisflight.org","url":"https://github.com/bretcope"}],"dependencies":{"debug":"*","fclone":"1.0.3"},"devDependencies":{"pm2-axon":"~2.0.11","better-assert":"*","mocha":"*"},"main":"index","scripts":{"test":"mocha --reporter spec"},"repository":{"type":"git","url":"git+https://github.com/unitech/pm2-axon-rpc.git"},"license":"MIT","gitHead":"5831dad9014dcbb698f40f1d77765f67281b9b2c","bugs":{"url":"https://github.com/unitech/pm2-axon-rpc/issues"},"homepage":"https://github.com/unitech/pm2-axon-rpc#readme","_id":"pm2-axon-rpc@0.4.3","_shasum":"433b1ded791cca078ec618d3be6a3d58d8a9adcb","_from":".","_npmVersion":"3.10.4","_nodeVersion":"4.4.4","_npmUser":{"name":"tknew","email":"strzelewicz.alexandre@gmail.com"},"dist":{"shasum":"433b1ded791cca078ec618d3be6a3d58d8a9adcb","tarball":"https://registry.npmjs.org/pm2-axon-rpc/-/pm2-axon-rpc-0.4.3.tgz"},"maintainers":[{"name":"tknew","email":"strzelewicz.alexandre@gmail.com"}],"_npmOperationalInternal":{"host":"packages-16-east.internal.npmjs.com","tmp":"tmp/pm2-axon-rpc-0.4.3.tgz_1467382301382_0.6346327208448201"},"directories":{}},"0.4.4":{"name":"pm2-axon-rpc","version":"0.4.4","description":"Remote procedure calls built on top of axon.","keywords":["axon","rpc","cloud"],"author":{"name":"TJ Holowaychuk","email":"tj@learnboost.com"},"contributors":[{"name":"Bret Copeland","email":"bret@atlantisflight.org","url":"https://github.com/bretcope"}],"dependencies":{"debug":"*","fclone":"1.0.3"},"devDependencies":{"pm2-axon":"~2.0.11","better-assert":"*","mocha":"*"},"main":"index","scripts":{"test":"mocha --reporter spec"},"repository":{"type":"git","url":"git+https://github.com/unitech/pm2-axon-rpc.git"},"license":"MIT","gitHead":"9db535e31ccdf73bd15d583df1bf2e381a588a69","bugs":{"url":"https://github.com/unitech/pm2-axon-rpc/issues"},"homepage":"https://github.com/unitech/pm2-axon-rpc#readme","_id":"pm2-axon-rpc@0.4.4","_shasum":"361f46b76a27e50795fd5d13e1e1623987bb17f4","_from":".","_npmVersion":"3.10.4","_nodeVersion":"4.4.4","_npmUser":{"name":"tknew","email":"strzelewicz.alexandre@gmail.com"},"dist":{"shasum":"361f46b76a27e50795fd5d13e1e1623987bb17f4","tarball":"https://registry.npmjs.org/pm2-axon-rpc/-/pm2-axon-rpc-0.4.4.tgz"},"maintainers":[{"name":"tknew","email":"strzelewicz.alexandre@gmail.com"}],"_npmOperationalInternal":{"host":"packages-12-west.internal.npmjs.com","tmp":"tmp/pm2-axon-rpc-0.4.4.tgz_1467797054238_0.33151634759269655"},"directories":{}},"0.4.5":{"name":"pm2-axon-rpc","version":"0.4.5","description":"Remote procedure calls built on top of axon.","keywords":["axon","rpc","cloud"],"author":{"name":"TJ Holowaychuk","email":"tj@learnboost.com"},"contributors":[{"name":"Bret Copeland","email":"bret@atlantisflight.org","url":"https://github.com/bretcope"}],"dependencies":{"debug":"*","fclone":"1.0.8"},"devDependencies":{"pm2-axon":"^3.0.2","better-assert":"*","mocha":"*"},"main":"index","scripts":{"test":"mocha --reporter spec"},"repository":{"type":"git","url":"git+https://github.com/unitech/pm2-axon-rpc.git"},"license":"MIT","gitHead":"d3d86cd288071a012e0d3b3aa8a7614559f72d45","bugs":{"url":"https://github.com/unitech/pm2-axon-rpc/issues"},"homepage":"https://github.com/unitech/pm2-axon-rpc#readme","_id":"pm2-axon-rpc@0.4.5","_shasum":"fb62e9a53f3e2b7bed1afe16e3b0d1b06fe8ba69","_from":".","_npmVersion":"3.9.6","_nodeVersion":"4.4.5","_npmUser":{"name":"tknew","email":"strzelewicz.alexandre@gmail.com"},"dist":{"shasum":"fb62e9a53f3e2b7bed1afe16e3b0d1b06fe8ba69","tarball":"https://registry.npmjs.org/pm2-axon-rpc/-/pm2-axon-rpc-0.4.5.tgz"},"maintainers":[{"name":"tknew","email":"strzelewicz.alexandre@gmail.com"}],"_npmOperationalInternal":{"host":"packages-12-west.internal.npmjs.com","tmp":"tmp/pm2-axon-rpc-0.4.5.tgz_1470527145918_0.14505457994528115"},"directories":{}},"0.4.6":{"name":"pm2-axon-rpc","version":"0.4.6","description":"Remote procedure calls built on top of axon.","keywords":["axon","rpc","cloud"],"author":{"name":"TJ Holowaychuk","email":"tj@learnboost.com"},"contributors":[{"name":"Bret Copeland","email":"bret@atlantisflight.org","url":"https://github.com/bretcope"}],"dependencies":{"debug":"*","fclone":"^1"},"devDependencies":{"pm2-axon":"^3.0.2","better-assert":"*","mocha":"*"},"main":"index","scripts":{"test":"mocha --reporter spec"},"repository":{"type":"git","url":"git+https://github.com/unitech/pm2-axon-rpc.git"},"license":"MIT","gitHead":"05024866fac0aa2757ca0f14e84310b5ac99d3c0","bugs":{"url":"https://github.com/unitech/pm2-axon-rpc/issues"},"homepage":"https://github.com/unitech/pm2-axon-rpc#readme","_id":"pm2-axon-rpc@0.4.6","_npmVersion":"5.3.0","_nodeVersion":"8.2.1","_npmUser":{"name":"tknew","email":"strzelewicz.alexandre@gmail.com"},"dist":{"integrity":"sha512-Cqa0Xoo4sCR74RRk4WRF12Iv6hNOUqeDjJEEBQnIkxffwH2t6tVDPR/IqIEU7lKdk0HQqj7EQ0ahxPqtB1LjhQ==","shasum":"0592772d7865b4d9406462039c36486599198e95","tarball":"https://registry.npmjs.org/pm2-axon-rpc/-/pm2-axon-rpc-0.4.6.tgz"},"maintainers":[{"name":"tknew","email":"strzelewicz.alexandre@gmail.com"}],"_npmOperationalInternal":{"host":"s3://npm-registry-packages","tmp":"tmp/pm2-axon-rpc-0.4.6.tgz_1501852397232_0.268049078527838"},"directories":{}},"0.5.0":{"name":"pm2-axon-rpc","version":"0.5.0","description":"Remote procedure calls built on top of axon.","keywords":["axon","rpc","cloud"],"author":{"name":"TJ Holowaychuk","email":"tj@learnboost.com"},"contributors":[{"name":"Bret Copeland","email":"bret@atlantisflight.org","url":"https://github.com/bretcope"}],"dependencies":{"debug":"^3.0","fclone":"^1"},"devDependencies":{"pm2-axon":"^3.0.2","better-assert":"*","mocha":"*"},"main":"index","scripts":{"test":"mocha --reporter spec"},"repository":{"type":"git","url":"git+https://github.com/unitech/pm2-axon-rpc.git"},"license":"MIT","gitHead":"c893bd08439a08d164af23696ea19d60e39d7a74","bugs":{"url":"https://github.com/unitech/pm2-axon-rpc/issues"},"homepage":"https://github.com/unitech/pm2-axon-rpc#readme","_id":"pm2-axon-rpc@0.5.0","_npmVersion":"5.3.0","_nodeVersion":"8.4.0","_npmUser":{"name":"tknew","email":"strzelewicz.alexandre@gmail.com"},"dist":{"integrity":"sha512-jKiAlnIitx+TtJ1++jThmN49gM0Dte4gm27Kqu2xAUQn33Rh9+5lOOqShS5Xbp0RPZL42hKNEgaVVOSqm3sJCg==","shasum":"ad08d6a27f580d5c7be4d7bf9dddff398f868994","tarball":"https://registry.npmjs.org/pm2-axon-rpc/-/pm2-axon-rpc-0.5.0.tgz"},"maintainers":[{"name":"tknew","email":"strzelewicz.alexandre@gmail.com"}],"_npmOperationalInternal":{"host":"s3://npm-registry-packages","tmp":"tmp/pm2-axon-rpc-0.5.0.tgz_1504692453575_0.7275731679983437"},"directories":{}}},"readme":"\n# axon-rpc\n\n[![Build Status](https://travis-ci.org/unitech/pm2-axon-rpc.png)](https://travis-ci.org/unitech/pm2-axon-rpc)\n\n  RPC client / server for [axon](https://github.com/visionmedia/axon).\n\n## arpc(1)\n\n  The `arpc(1)` executable allows you to expose entire\n  node modules with a single command, or inspect\n  methods exposed by a given node.\n\n```\n\nUsage: arpc [options] <module>\n\nOptions:\n\n  -h, --help            output usage information\n  -V, --version         output the version number\n  -a, --addr <addr>     bind to the given <addr>\n  -m, --methods <addr>  inspect methods exposed by <addr>\n\n```\n\n## Server\n\n```js\nvar rpc = require('axon-rpc')\n  , axon = require('axon')\n  , rep = axon.socket('rep');\n\nvar server = new rpc.Server(rep);\nrep.bind(4000);\n```\n\n### Server#expose(name, fn)\n\n  Expose a single method `name` mapped to `fn` callback.\n\n```js\nserver.expose('add', function(a, b, fn){\n  fn(null, a + b);\n});\n```\n\n### Server#expose(object)\n\n  Expose several methods:\n\n```js\nserver.expose({\n  add: function(){ ... },\n  sub: function(){ ... }\n});\n```\n\n  This may also be used to expose\n  an entire node module with exports:\n\n```js\nserver.expose(require('./api'));\n```\n\n## Client\n\n```js\nvar rpc = require('axon-rpc')\n  , axon = require('axon')\n  , req = axon.socket('req');\n\nvar client = new rpc.Client(req);\nreq.connect(4000);\n```\n\n### Client#call(name, ..., fn)\n\n  Invoke method `name` with some arguments and invoke `fn(err, ...)`:\n\n```js\nclient.call('add', 1, 2, function(err, n){\n  console.log(n);\n  // => 3\n})\n```\n\n### Client#methods(fn)\n\n  Request available methods:\n\n```js\nclient.methods(function(err, methods){\n  console.log(methods);\n})\n```\n\n  Responds with objects such as:\n\n```js\n{\n  add: {\n    name: 'add',\n    params: ['a', 'b', 'fn']\n  }\n}\n```\n\n## License\n\n(The MIT License)\n\nCopyright (c) 2014 TJ Holowaychuk &lt;tj@learnboost.com&gt;\n\nPermission is hereby granted, free of charge, to any person obtaining\na copy of this software and associated documentation files (the\n'Software'), to deal in the Software without restriction, including\nwithout limitation the rights to use, copy, modify, merge, publish,\ndistribute, sublicense, and/or sell copies of the Software, and to\npermit persons to whom the Software is furnished to do so, subject to\nthe following conditions:\n\nThe above copyright notice and this permission notice shall be\nincluded in all copies or substantial portions of the Software.\n\nTHE SOFTWARE IS PROVIDED 'AS IS', WITHOUT WARRANTY OF ANY KIND,\nEXPRESS OR IMPLIED, INCLUDING BUT NOT LIMITED TO THE WARRANTIES OF\nMERCHANTABILITY, FITNESS FOR A PARTICULAR PURPOSE AND NONINFRINGEMENT.\nIN NO EVENT SHALL THE AUTHORS OR COPYRIGHT HOLDERS BE LIABLE FOR ANY\nCLAIM, DAMAGES OR OTHER LIABILITY, WHETHER IN AN ACTION OF CONTRACT,\nTORT OR OTHERWISE, ARISING FROM, OUT OF OR IN CONNECTION WITH THE\nSOFTWARE OR THE USE OR OTHER DEALINGS IN THE SOFTWARE.\n","maintainers":[{"name":"tknew","email":"strzelewicz.alexandre@gmail.com"}],"time":{"modified":"2017-09-08T11:21:15.466Z","created":"2014-05-14T14:36:24.016Z","0.0.2":"2014-05-14T14:36:24.016Z","0.2.0":"2014-08-18T13:09:09.989Z","0.2.1":"2014-08-19T13:49:53.254Z","0.3.1":"2014-08-30T13:34:07.099Z","0.3.2":"2014-09-17T15:23:39.617Z","0.3.3":"2014-09-18T17:03:36.096Z","0.3.4":"2014-09-30T10:14:08.063Z","0.3.5":"2014-09-30T12:16:54.192Z","0.3.6":"2014-10-11T13:18:19.794Z","0.4.0":"2016-06-13T21:25:26.846Z","0.4.2":"2016-07-01T14:10:54.553Z","0.4.3":"2016-07-01T14:11:43.626Z","0.4.4":"2016-07-06T09:24:16.662Z","0.4.5":"2016-08-06T23:45:46.186Z","0.4.6":"2017-08-04T13:13:18.177Z","0.5.0":"2017-09-06T10:07:34.499Z"},"keywords":["axon","rpc","cloud"],"author":{"name":"TJ Holowaychuk","email":"tj@learnboost.com"},"readmeFilename":"Readme.md","homepage":"https://github.com/unitech/pm2-axon-rpc#readme","repository":{"type":"git","url":"git+https://github.com/unitech/pm2-axon-rpc.git"},"contributors":[{"name":"Bret Copeland","email":"bret@atlantisflight.org","url":"https://github.com/bretcope"}],"bugs":{"url":"https://github.com/unitech/pm2-axon-rpc/issues"},"license":"MIT","users":{"brandonpapworth":true,"tmurngon":true,"johnsmithcoder":true},"_attachments":{},"_etag":"W/\"59b27d2b-5f3e\"","_lastModified":"Fri, 08 Sep 2017 11:21:15 GMT"}